csp_py/__init__.py
csp_py/crc32.py
csp_py/interface.py
csp_py/node.py
csp_py/packet.py
csp_py/packet_handler.py
csp_py/py.typed
csp_py/router.py
csp_py/rtable.py
csp_py/socket.py
csp_py/interfaces/interface_pair.py
csp_py/interfaces/lo_interface.py
csp_py/interfaces/serializing_interface.py
csp_py/interfaces/can/__init__.py
csp_py/interfaces/can/can_interface.py
csp_py/services/ping.py
csp_py/services/ping_client.py
cubesat_space_protocol_py-1.1.3.dist-info/METADATA
cubesat_space_protocol_py-1.1.3.dist-info/WHEEL
cubesat_space_protocol_py-1.1.3.dist-info/licenses/LICENSE
cubesat_space_protocol_py-1.1.3.dist-info/RECORD
