Metadata-Version: 2.4
Name: cubesat-space-protocol-py
Version: 1.1.3
Summary: Cubsat Space Protocol (CSP) native Python implementation
Author: KP Labs
License-Expression: MIT
License-File: LICENSE
Classifier: License :: OSI Approved :: MIT License
Classifier: Operating System :: OS Independent
Requires-Python: >=3.12
